pyktok/__init__.py
pyktok/pyktok.py
pyktok-0.0.31.dist-info/METADATA
pyktok-0.0.31.dist-info/WHEEL
pyktok-0.0.31.dist-info/licenses/LICENSE
pyktok-0.0.31.dist-info/RECORD
