Metadata-Version: 2.4
Name: pyktok
Version: 0.0.31
Summary: A package for collecting TikTok videos and metadata.
Project-URL: Homepage, https://github.com/dfreelon/pyktok
Author-email: Deen Freelon <dfreelon@gmail.com>
License: BSD 3-Clause License
License-File: LICENSE
Classifier: License :: OSI Approved :: BSD License
Classifier: Operating System :: OS Independent
Classifier: Programming Language :: Python :: 3
Requires-Python: >=3.10
Requires-Dist: beautifulsoup4
Requires-Dist: browser-cookie3
Requires-Dist: numpy
Requires-Dist: pandas
Requires-Dist: playwright>=1.50.0
Requires-Dist: requests
Requires-Dist: streamlit
Requires-Dist: tiktokapi>=7.0.0
